ploteris/__init__.py
ploteris/duomenys.py
ploteris/main.py
ploteris/ploteris.py
ploteris-0.1.2.dist-info/METADATA
ploteris-0.1.2.dist-info/WHEEL
ploteris-0.1.2.dist-info/top_level.txt
ploteris-0.1.2.dist-info/RECORD
