Metadata-Version: 2.1
Name: ploteris
Version: 0.1.2
Author: lmacionis
Author-email: lmacionis@yahoo.com
Requires-Python: >=3.6
Requires-Dist: numpy
Requires-Dist: contourpy ==1.3.0
Requires-Dist: cycler ==0.12.1
Requires-Dist: fonttools ==4.54.1
Requires-Dist: kiwisolver ==1.4.7
Requires-Dist: matplotlib ==3.9.2
Requires-Dist: packaging ==24.1
Requires-Dist: pillow ==11.0.0
Requires-Dist: pyparsing ==3.2.0
Requires-Dist: python-dateutil ==2.9.0.post0
Requires-Dist: six ==1.16.0
